feincms_simpletable/__init__.py
feincms_simpletable/models.py
feincms_simpletable/tests.py
feincms_simpletable/locale/ru/LC_MESSAGES/django.mo
feincms_simpletable/locale/ru/LC_MESSAGES/django.po
feincms_simpletable/templates/content/simpletable/_body_default.html
feincms_simpletable/templates/content/simpletable/_body_headless.html
feincms_simpletable/templates/content/simpletable/default.html
feincms_simpletable/templates/content/simpletable/headless.html
feincms_simpletable/templates/content/simpletable/prerendered.html
feincms_simpletable-0.4.0.dist-info/METADATA
feincms_simpletable-0.4.0.dist-info/RECORD
feincms_simpletable-0.4.0.dist-info/WHEEL
feincms_simpletable-0.4.0.dist-info/top_level.txt
