Metadata-Version: 2.1
Name: feincms-simpletable
Version: 0.4.0
Summary: Table content type for feincms: copy-paste cells from spreadsheets to admin, get them displayed as html table on your website
Home-page: https://github.com/paramono/feincms_simpletable
Author: Alexander Paramonov
Author-email: alex@paramono.com
License: BSD License
Platform: UNKNOWN
Classifier: Environment :: Web Environment
Classifier: Framework :: Django
Classifier: Intended Audience :: Developers
Classifier: License :: OSI Approved :: BSD License
Classifier: Operating System :: OS Independent
Classifier: Programming Language :: Python
Classifier: Programming Language :: Python :: 3
Classifier: Programming Language :: Python :: 3.2
Classifier: Programming Language :: Python :: 3.3
Classifier: Programming Language :: Python :: 3.4
Classifier: Topic :: Internet :: WWW/HTTP
Classifier: Topic :: Internet :: WWW/HTTP :: Dynamic Content
